speedup/speedup.py
speedup.py-2023.10.19.dist-info/METADATA
speedup.py-2023.10.19.dist-info/WHEEL
speedup.py-2023.10.19.dist-info/entry_points.txt
speedup.py-2023.10.19.dist-info/top_level.txt
speedup.py-2023.10.19.dist-info/RECORD
